{
	"name": "میله",
	"plugin-id": "Sprite",
	"sid": 257329161462332,
	"isGlobal": false,
	"editorNewInstanceIsReplica": true,
	"instanceVariables": [],
	"behaviorTypes": [
		{
			"behaviorId": "MoveTo",
			"name": "MoveTo",
			"sid": 619753844613110
		}
	],
	"effectTypes": [],
	"animations": {
		"items": [
			{
				"frames": [
					{
						"width": 1024,
						"height": 1024,
						"originX": 0.5,
						"originY": 0.47402608315686867,
						"originalSource": "",
						"exportFormat": "lossless",
						"exportQuality": 0.8,
						"fileType": "image/png",
						"imageSpriteId": 8497081,
						"collisionPoly": {
							"points": [
								0.9942633619104208,
								0.0017730496453900457,
								0.9942633619104208,
								0.99822695035461,
								0.005736638089579249,
								0.99822695035461,
								0.005736638089579249,
								0.0017730496453900457
							]
						},
						"useCollisionPoly": true,
						"duration": 1,
						"tag": ""
					}
				],
				"sid": 447867749086027,
				"name": "Animation 1",
				"isLooping": false,
				"isPingPong": false,
				"repeatCount": 1,
				"repeatTo": 0,
				"speed": 5
			}
		],
		"subfolders": []
	}
}